kafka_utils/__init__.py
kafka_utils/base_consumer.py
kafka_utils/base_producer.py
kafka_utils_evcom-0.0.1.dist-info/LICENSE
kafka_utils_evcom-0.0.1.dist-info/METADATA
kafka_utils_evcom-0.0.1.dist-info/WHEEL
kafka_utils_evcom-0.0.1.dist-info/top_level.txt
kafka_utils_evcom-0.0.1.dist-info/RECORD
